{
  "ComponentIndexes": {},
  "ControlUniqueGuids": {},
  "ControlUniqueIds": {
    "App": 1,
    "ApprovalPage": 60,
    "Attachments_DataCard1": 224,
    "Attachments_DataCard5": 46,
    "Attachments_DataCard6": 346,
    "Attachments_DataCard7": 271,
    "btn_approval": 144,
    "btn_approval_1": 352,
    "btn_approval_2": 277,
    "btn_HOD": 153,
    "btn_reject": 353,
    "btn_reject_1": 278,
    "btnLogin": 190,
    "Button_Cancel_10": 361,
    "Button_Cancel_11": 287,
    "Button_Cancel_14": 59,
    "Button_newticket": 230,
    "Button_OK_12": 58,
    "Button_OK_8": 360,
    "Button_OK_9": 286,
    "Container1": 111,
    "Container10": 5,
    "Container10_1": 232,
    "Container10_2": 307,
    "Container10_3": 355,
    "Container10_4": 280,
    "Container11": 229,
    "Container12": 289,
    "Container13": 237,
    "Container13_6": 52,
    "Container14": 294,
    "Container15": 312,
    "Container15_1": 359,
    "Container15_2": 285,
    "Container16": 70,
    "Container16_1": 356,
    "Container16_2": 281,
    "Container17": 71,
    "Container18": 74,
    "Container19": 86,
    "Container2": 112,
    "Container2_1": 193,
    "Container2_2": 157,
    "Container2_3": 6,
    "Container2_4": 161,
    "Container2_5": 290,
    "Container2_6": 62,
    "Container2_7": 233,
    "Container2_8": 87,
    "Container2_9": 308,
    "Container20": 351,
    "Container20_1": 276,
    "Container21": 75,
    "Container23": 76,
    "Container24": 79,
    "Container25": 95,
    "Container26": 96,
    "Container27": 99,
    "Container28": 100,
    "Container28_4": 57,
    "Container29": 101,
    "Container3": 116,
    "Container30": 104,
    "Container31": 168,
    "Container32": 169,
    "Container33": 172,
    "Container34": 173,
    "Container35": 174,
    "Container36": 177,
    "Container37": 12,
    "Container38": 197,
    "Container39": 119,
    "Container4": 117,
    "Container4_1": 187,
    "Container40": 123,
    "Container41": 127,
    "Container42": 54,
    "Container42_4": 53,
    "Container43": 132,
    "Container44": 136,
    "Container45": 140,
    "Container46": 297,
    "Container47": 298,
    "Container48": 300,
    "Container49": 301,
    "Container5": 130,
    "Container50": 282,
    "Container6": 146,
    "Container7": 192,
    "Container8": 184,
    "Container9": 156,
    "Container9_1": 61,
    "ContainerApproval": 143,
    "ContainerHOD": 152,
    "Created By_DataCard1": 41,
    "Created By_DataCard1_1": 266,
    "Created By_DataCard1_2": 341,
    "Created_DataCard1": 38,
    "Created_DataCard1_1": 263,
    "Created_DataCard1_2": 338,
    "DataCardKey1": 201,
    "DataCardKey10": 216,
    "DataCardKey11": 221,
    "DataCardKey12": 226,
    "DataCardKey13": 206,
    "DataCardKey14": 15,
    "DataCardKey14_1": 240,
    "DataCardKey14_2": 315,
    "DataCardKey17": 35,
    "DataCardKey17_1": 260,
    "DataCardKey17_2": 335,
    "DataCardKey20": 19,
    "DataCardKey20_1": 244,
    "DataCardKey20_2": 319,
    "DataCardKey22": 27,
    "DataCardKey22_1": 252,
    "DataCardKey22_2": 327,
    "DataCardKey23": 23,
    "DataCardKey23_1": 248,
    "DataCardKey23_2": 323,
    "DataCardKey24": 31,
    "DataCardKey24_1": 256,
    "DataCardKey24_2": 331,
    "DataCardKey26": 39,
    "DataCardKey26_1": 264,
    "DataCardKey26_2": 339,
    "DataCardKey27": 43,
    "DataCardKey27_1": 268,
    "DataCardKey27_2": 343,
    "DataCardKey5": 48,
    "DataCardKey6": 348,
    "DataCardKey7": 273,
    "DataCardKey9": 211,
    "DataCardValue1": 202,
    "DataCardValue10": 222,
    "DataCardValue11": 227,
    "DataCardValue12": 207,
    "DataCardValue13": 16,
    "DataCardValue13_1": 241,
    "DataCardValue13_2": 316,
    "DataCardValue16": 36,
    "DataCardValue16_1": 261,
    "DataCardValue16_2": 336,
    "DataCardValue19": 20,
    "DataCardValue19_1": 245,
    "DataCardValue19_2": 320,
    "DataCardValue21": 28,
    "DataCardValue21_1": 253,
    "DataCardValue21_2": 328,
    "DataCardValue22": 24,
    "DataCardValue22_1": 249,
    "DataCardValue22_2": 324,
    "DataCardValue23": 32,
    "DataCardValue23_1": 257,
    "DataCardValue23_2": 332,
    "DataCardValue25": 40,
    "DataCardValue25_1": 265,
    "DataCardValue25_2": 340,
    "DataCardValue26": 44,
    "DataCardValue26_1": 269,
    "DataCardValue26_2": 344,
    "DataCardValue5": 49,
    "DataCardValue6": 349,
    "DataCardValue7": 274,
    "DataCardValue8": 212,
    "DataCardValue9": 217,
    "Dialog_commentapproval": 279,
    "Dialog_commentHOD": 354,
    "Dialog_delete": 51,
    "ErrorMessage1": 203,
    "ErrorMessage10": 218,
    "ErrorMessage11": 223,
    "ErrorMessage12": 228,
    "ErrorMessage13": 208,
    "ErrorMessage16": 37,
    "ErrorMessage16_1": 262,
    "ErrorMessage16_2": 337,
    "ErrorMessage18": 21,
    "ErrorMessage18_1": 246,
    "ErrorMessage18_2": 321,
    "ErrorMessage20": 29,
    "ErrorMessage20_1": 254,
    "ErrorMessage20_2": 329,
    "ErrorMessage22": 45,
    "ErrorMessage22_1": 270,
    "ErrorMessage22_2": 345,
    "ErrorMessage5": 50,
    "ErrorMessage6": 350,
    "ErrorMessage7": 275,
    "ErrorMessage9": 213,
    "FilterByGallery": 295,
    "Form1": 198,
    "FormDetail_approval": 238,
    "FormDetail_user": 13,
    "FormDetail_user_2": 313,
    "Gallery1": 147,
    "galleryTemplate1": 148,
    "galleryTemplate1_2": 296,
    "galleryTemplate2": 165,
    "galleryTemplate2_1": 67,
    "galleryTemplate2_2": 92,
    "Group ,New Tickets": 122,
    "Group, All Ticket": 118,
    "Group, on hold": 131,
    "Group,Tickets Approval": 126,
    "Group21": 135,
    "Group6": 139,
    "Heading1": 170,
    "Heading1_1": 72,
    "Heading1_2": 171,
    "Heading1_3": 73,
    "Heading1_4": 98,
    "Heading1_5": 97,
    "HODPage": 85,
    "HomePage": 110,
    "Host": 3,
    "Icon1": 115,
    "Icon1_1": 194,
    "Icon1_10": 88,
    "Icon1_13": 309,
    "Icon1_2": 158,
    "Icon1_3": 9,
    "Icon1_4": 162,
    "Icon1_5": 7,
    "Icon1_6": 8,
    "Icon1_7": 291,
    "Icon1_8": 63,
    "Icon1_9": 234,
    "Icon2": 113,
    "icon3_2": 302,
    "icon8": 180,
    "icon8_1": 82,
    "icon8_2": 107,
    "Image1": 114,
    "Image1_1": 196,
    "Image1_2": 160,
    "Image1_3": 292,
    "Image1_4": 64,
    "Image1_5": 89,
    "Image1_6": 310,
    "Image1_7": 236,
    "Image1_8": 11,
    "Image2": 186,
    "Label1": 55,
    "Label1_1": 195,
    "Label1_2": 159,
    "Label1_3": 10,
    "Label1_4": 293,
    "Label1_5": 65,
    "Label1_6": 90,
    "Label1_7": 235,
    "Label1_8": 311,
    "Label1_9": 185,
    "Label2": 163,
    "Label2_1": 188,
    "Label3": 283,
    "Label4": 357,
    "LoginPage": 183,
    "NewTicketPage": 191,
    "NextArrow2": 151,
    "NextArrow2_2": 154,
    "NextArrow2_3": 145,
    "Rectangle1_12": 182,
    "Rectangle1_13": 84,
    "Rectangle1_14": 109,
    "Rectangle13_1": 299,
    "Rectangle14": 181,
    "Rectangle14_1": 83,
    "Rectangle14_2": 108,
    "Rectangle15": 167,
    "Rectangle15_1": 69,
    "Rectangle15_2": 94,
    "Rectangle2_18": 305,
    "Rectangle6": 166,
    "Rectangle6_1": 68,
    "Rectangle6_2": 93,
    "Rectangle7_1": 304,
    "ReqDescription_DataCard1": 219,
    "ReqDescription_DataCard2": 30,
    "ReqDescription_DataCard2_1": 255,
    "ReqDescription_DataCard2_2": 330,
    "ReqPermission_DataCard1": 209,
    "ReqPermission_DataCard2": 25,
    "ReqPermission_DataCard2_1": 250,
    "ReqPermission_DataCard2_2": 325,
    "ReqReason_DataCard1": 214,
    "ReqReason_DataCard2": 22,
    "ReqReason_DataCard2_1": 247,
    "ReqReason_DataCard2_2": 322,
    "ReqType_DataCard2": 204,
    "ReqType_DataCard3": 17,
    "ReqType_DataCard3_1": 242,
    "ReqType_DataCard3_2": 317,
    "Separator2": 149,
    "StarVisible1": 200,
    "StarVisible10": 215,
    "StarVisible11": 220,
    "StarVisible12": 225,
    "StarVisible13": 205,
    "StarVisible16": 34,
    "StarVisible16_1": 259,
    "StarVisible16_2": 334,
    "StarVisible18": 18,
    "StarVisible18_1": 243,
    "StarVisible18_2": 318,
    "StarVisible20": 26,
    "StarVisible20_1": 251,
    "StarVisible20_2": 326,
    "StarVisible22": 42,
    "StarVisible22_1": 267,
    "StarVisible22_2": 342,
    "StarVisible5": 47,
    "StarVisible6": 347,
    "StarVisible7": 272,
    "StarVisible9": 210,
    "Status_DataCard2": 33,
    "Status_DataCard2_1": 258,
    "Status_DataCard2_2": 333,
    "Subtitle1": 175,
    "Subtitle1_1": 179,
    "Subtitle1_10": 80,
    "Subtitle1_11": 105,
    "Subtitle1_2": 77,
    "Subtitle1_3": 81,
    "Subtitle1_4": 103,
    "Subtitle1_5": 106,
    "Subtitle1_6": 178,
    "Subtitle1_7": 176,
    "Subtitle1_8": 78,
    "Subtitle1_9": 102,
    "TextBox2": 121,
    "TextBox2_1": 125,
    "TextBox2_10": 128,
    "TextBox2_11": 129,
    "TextBox2_2": 138,
    "TextBox2_3": 142,
    "TextBox2_4": 134,
    "TextBox2_5": 120,
    "TextBox2_6": 124,
    "TextBox2_7": 137,
    "TextBox2_8": 141,
    "TextBox2_9": 133,
    "TextBox3_2": 303,
    "TextInput1": 358,
    "TextInput1_1": 284,
    "TextInput1_4": 56,
    "TicketFilterPage": 288,
    "TicketPage": 155,
    "TicketsDetailPage_Approval": 231,
    "TicketsDetailPage_HOD": 306,
    "TicketsDetailPage_User": 4,
    "TicketsGallery": 164,
    "TicketsGallery_approval": 66,
    "TicketsGallery_HOD": 91,
    "Title_DataCard1": 199,
    "Title_DataCard2": 14,
    "Title_DataCard2_1": 239,
    "Title_DataCard2_2": 314,
    "Title2": 150,
    "txtEmail": 189
  },
  "FunctionParamsInvariantScripts": {},
  "FunctionParamsInvariantScriptsOnInstances": {},
  "HeaderLastSavedDateTimeUTC": "10/06/2023 04:13:55",
  "IsLegacyComponentAllowGlobalScopeCase": false,
  "LocalConnectionIDReferences": {
    "38e06757-82fb-4679-ac8e-ca5ed276e924": "\"/providers/microsoft.powerapps/apis/shared_office365users/connections/472171f27f604a209b175797c44214e4\"",
    "65812730-5db3-41bc-a8ca-ec1f2d3d88b1": "\"/providers/microsoft.powerapps/apis/shared_logicflows/connections/b344e347bfff7a29ef20959b6a6e9c53-3e32093d8903a868\"",
    "7776555d-977e-44f7-bd77-d4fe047f3143": "\"/providers/microsoft.powerapps/apis/shared_logicflows/connections/c9a0ab277aacbc4bd2a13b7578b4b685-3e32093d8903a868\"",
    "a965592d-aebd-42f7-bd1b-ab864595125d": "\"/providers/microsoft.powerapps/apis/shared_sharepointonline/connections/shared-sharepointonl-92c111f4-e7f8-48f8-92c0-19724e02c6cf\""
  },
  "LocalDatabaseReferencesAsEmpty": false,
  "LocalResourceFileNames": {
    "Logo - PizzaHut": "0001.png",
    "logocochu": "2da7aef0-ea6b-4e49-bf9b-128e849cd2d0.png",
    "pizzahut1": "0002.png"
  },
  "LocalResourceRootPaths": {
    "Logo - PizzaHut": "https://docserverpwaprodeas.blob.core.windows.net/366c7f53-1c74-4b5a-aa8e-071e1c14056f-1/resource/Assets0Images00001.png?skoid=58690ece-ec83-4ce2-9ce8-883d4d6a54ee&sktid=975f013f-7f24-47e8-a7d3-abc4752bf346&skt=2023-10-06T04%3A11%3A10Z&ske=2023-10-07T04%3A26%3A10Z&sks=b&skv=2021-08-06&sv=2021-08-06&spr=https&se=2023-10-07T04%3A26%3A10Z&sr=b&sp=r&sig=61A90pp1xzG%2FnT%2FPuoKSGfsRwCPCGsqaUZuBkkc7axw%3D",
    "logocochu": "https://docserverpwaprodeas.blob.core.windows.net/366c7f53-1c74-4b5a-aa8e-071e1c14056f-1/resource/Assets0Images02da7aef0-ea6b-4e49-bf9b-128e849cd2d0.png?skoid=58690ece-ec83-4ce2-9ce8-883d4d6a54ee&sktid=975f013f-7f24-47e8-a7d3-abc4752bf346&skt=2023-10-06T04%3A11%3A10Z&ske=2023-10-07T04%3A26%3A10Z&sks=b&skv=2021-08-06&sv=2021-08-06&spr=https&se=2023-10-07T04%3A26%3A10Z&sr=b&sp=r&sig=BC5rX6peGcdVz00bzWQpUkqfRQJTkX%2BCRyJDB6eNKt8%3D",
    "pizzahut1": "https://docserverpwaprodeas.blob.core.windows.net/366c7f53-1c74-4b5a-aa8e-071e1c14056f-1/resource/Assets0Images00002.png?skoid=58690ece-ec83-4ce2-9ce8-883d4d6a54ee&sktid=975f013f-7f24-47e8-a7d3-abc4752bf346&skt=2023-10-06T04%3A11%3A10Z&ske=2023-10-07T04%3A26%3A10Z&sks=b&skv=2021-08-06&sv=2021-08-06&spr=https&se=2023-10-07T04%3A26%3A10Z&sr=b&sp=r&sig=b3F3Hhw9emjhTvAMKnCP5zGbFtm%2F0zty5p12%2BiVdNiI%3D"
  },
  "OldLogoFileName": "logo.jpg",
  "OrderComponentMetadata": {},
  "OrderComponentTemplate": {},
  "OrderDataSource": {
    "AccountName": 3,
    "AccountNameTypes": 4,
    "Attendants": 5,
    "CardStackGallerySample": 6,
    "CaseStatus": 7,
    "CollectRequest": 25,
    "ComboBoxSample": 8,
    "CustomGallerySample": 9,
    "DropDownSample": 10,
    "Filterby": 11,
    "FilterTickets": 12,
    "Getrandompasswords": 0,
    "LevelApproveTest": 13,
    "Login2": 1,
    "Office365Users": 2,
    "PriorityDropdown": 14,
    "PriorityTypes": 15,
    "ReqProcessTest": 16,
    "ReqTypeTest": 17,
    "Request_Test": 18,
    "Setting_LevelApprove": 20,
    "SettingTest": 19,
    "TableTicketTypes_Test": 21,
    "TextualGallerySample": 22,
    "Tickets": 23,
    "TicketTypes": 24
  },
  "OrderGroupControls": {},
  "OrderPcfTemplate": {},
  "OrderTemplate": {},
  "OrderXMLTemplate": {
    "attachments": 6,
    "button": 8,
    "combobox": 5,
    "form": 11,
    "formViewer": 4,
    "gallery": 9,
    "groupContainer": 0,
    "icon": 1,
    "image": 3,
    "label": 2,
    "rectangle": 10,
    "text": 7
  },
  "OverridablePropertiesEntry": {
    "App": {},
    "ApprovalPage": {},
    "Attachments_DataCard1": {},
    "Attachments_DataCard5": {},
    "Attachments_DataCard6": {},
    "Attachments_DataCard7": {},
    "btn_approval": {},
    "btn_approval_1": {},
    "btn_approval_2": {},
    "btn_HOD": {},
    "btn_reject": {},
    "btn_reject_1": {},
    "btnLogin": {},
    "Button_Cancel_10": {},
    "Button_Cancel_11": {},
    "Button_Cancel_14": {},
    "Button_newticket": {},
    "Button_OK_12": {},
    "Button_OK_8": {},
    "Button_OK_9": {},
    "Container1": {},
    "Container10": {},
    "Container10_1": {},
    "Container10_2": {},
    "Container10_3": {},
    "Container10_4": {},
    "Container11": {},
    "Container12": {},
    "Container13": {},
    "Container13_6": {},
    "Container14": {},
    "Container15": {},
    "Container15_1": {},
    "Container15_2": {},
    "Container16": {},
    "Container16_1": {},
    "Container16_2": {},
    "Container17": {},
    "Container18": {},
    "Container19": {},
    "Container2": {},
    "Container2_1": {},
    "Container2_2": {},
    "Container2_3": {},
    "Container2_4": {},
    "Container2_5": {},
    "Container2_6": {},
    "Container2_7": {},
    "Container2_8": {},
    "Container2_9": {},
    "Container20": {},
    "Container20_1": {},
    "Container21": {},
    "Container23": {},
    "Container24": {},
    "Container25": {},
    "Container26": {},
    "Container27": {},
    "Container28": {},
    "Container28_4": {},
    "Container29": {},
    "Container3": {},
    "Container30": {},
    "Container31": {},
    "Container32": {},
    "Container33": {},
    "Container34": {},
    "Container35": {},
    "Container36": {},
    "Container37": {},
    "Container38": {},
    "Container39": {},
    "Container4": {},
    "Container4_1": {},
    "Container40": {},
    "Container41": {},
    "Container42": {},
    "Container42_4": {},
    "Container43": {},
    "Container44": {},
    "Container45": {},
    "Container46": {},
    "Container47": {},
    "Container48": {},
    "Container49": {},
    "Container5": {},
    "Container50": {},
    "Container6": {},
    "Container7": {},
    "Container8": {},
    "Container9": {},
    "Container9_1": {},
    "ContainerApproval": {},
    "ContainerHOD": {},
    "Created By_DataCard1": {},
    "Created By_DataCard1_1": {},
    "Created By_DataCard1_2": {},
    "Created_DataCard1": {},
    "Created_DataCard1_1": {},
    "Created_DataCard1_2": {},
    "DataCardKey1": {},
    "DataCardKey10": {},
    "DataCardKey11": {},
    "DataCardKey12": {},
    "DataCardKey13": {},
    "DataCardKey14": {},
    "DataCardKey14_1": {},
    "DataCardKey14_2": {},
    "DataCardKey17": {},
    "DataCardKey17_1": {},
    "DataCardKey17_2": {},
    "DataCardKey20": {},
    "DataCardKey20_1": {},
    "DataCardKey20_2": {},
    "DataCardKey22": {},
    "DataCardKey22_1": {},
    "DataCardKey22_2": {},
    "DataCardKey23": {},
    "DataCardKey23_1": {},
    "DataCardKey23_2": {},
    "DataCardKey24": {},
    "DataCardKey24_1": {},
    "DataCardKey24_2": {},
    "DataCardKey26": {},
    "DataCardKey26_1": {},
    "DataCardKey26_2": {},
    "DataCardKey27": {},
    "DataCardKey27_1": {},
    "DataCardKey27_2": {},
    "DataCardKey5": {},
    "DataCardKey6": {},
    "DataCardKey7": {},
    "DataCardKey9": {},
    "DataCardValue1": {},
    "DataCardValue10": {},
    "DataCardValue11": {},
    "DataCardValue12": {},
    "DataCardValue13": {},
    "DataCardValue13_1": {},
    "DataCardValue13_2": {},
    "DataCardValue16": {},
    "DataCardValue16_1": {},
    "DataCardValue16_2": {},
    "DataCardValue19": {},
    "DataCardValue19_1": {},
    "DataCardValue19_2": {},
    "DataCardValue21": {},
    "DataCardValue21_1": {},
    "DataCardValue21_2": {},
    "DataCardValue22": {},
    "DataCardValue22_1": {},
    "DataCardValue22_2": {},
    "DataCardValue23": {},
    "DataCardValue23_1": {},
    "DataCardValue23_2": {},
    "DataCardValue25": {},
    "DataCardValue25_1": {},
    "DataCardValue25_2": {},
    "DataCardValue26": {},
    "DataCardValue26_1": {},
    "DataCardValue26_2": {},
    "DataCardValue5": {},
    "DataCardValue6": {},
    "DataCardValue7": {},
    "DataCardValue8": {},
    "DataCardValue9": {},
    "Dialog_commentapproval": {},
    "Dialog_commentHOD": {},
    "Dialog_delete": {},
    "ErrorMessage1": {},
    "ErrorMessage10": {},
    "ErrorMessage11": {},
    "ErrorMessage12": {},
    "ErrorMessage13": {},
    "ErrorMessage16": {},
    "ErrorMessage16_1": {},
    "ErrorMessage16_2": {},
    "ErrorMessage18": {},
    "ErrorMessage18_1": {},
    "ErrorMessage18_2": {},
    "ErrorMessage20": {},
    "ErrorMessage20_1": {},
    "ErrorMessage20_2": {},
    "ErrorMessage22": {},
    "ErrorMessage22_1": {},
    "ErrorMessage22_2": {},
    "ErrorMessage5": {},
    "ErrorMessage6": {},
    "ErrorMessage7": {},
    "ErrorMessage9": {},
    "FilterByGallery": {},
    "Form1": {},
    "FormDetail_approval": {},
    "FormDetail_user": {},
    "FormDetail_user_2": {},
    "Gallery1": {},
    "galleryTemplate1": {},
    "galleryTemplate1_2": {},
    "galleryTemplate2": {},
    "galleryTemplate2_1": {},
    "galleryTemplate2_2": {},
    "Group ,New Tickets": {},
    "Group, All Ticket": {},
    "Group, on hold": {},
    "Group,Tickets Approval": {},
    "Group21": {},
    "Group6": {},
    "Heading1": {},
    "Heading1_1": {},
    "Heading1_2": {},
    "Heading1_3": {},
    "Heading1_4": {},
    "Heading1_5": {},
    "HODPage": {},
    "HomePage": {},
    "Host": {},
    "Icon1": {},
    "Icon1_1": {},
    "Icon1_10": {},
    "Icon1_13": {},
    "Icon1_2": {},
    "Icon1_3": {},
    "Icon1_4": {},
    "Icon1_5": {},
    "Icon1_6": {},
    "Icon1_7": {},
    "Icon1_8": {},
    "Icon1_9": {},
    "Icon2": {},
    "icon3_2": {},
    "icon8": {},
    "icon8_1": {},
    "icon8_2": {},
    "Image1": {},
    "Image1_1": {},
    "Image1_2": {},
    "Image1_3": {},
    "Image1_4": {},
    "Image1_5": {},
    "Image1_6": {},
    "Image1_7": {},
    "Image1_8": {},
    "Image2": {},
    "Label1": {},
    "Label1_1": {},
    "Label1_2": {},
    "Label1_3": {},
    "Label1_4": {},
    "Label1_5": {},
    "Label1_6": {},
    "Label1_7": {},
    "Label1_8": {},
    "Label1_9": {},
    "Label2": {},
    "Label2_1": {},
    "Label3": {},
    "Label4": {},
    "LoginPage": {},
    "NewTicketPage": {},
    "NextArrow2": {},
    "NextArrow2_2": {},
    "NextArrow2_3": {},
    "Rectangle1_12": {},
    "Rectangle1_13": {},
    "Rectangle1_14": {},
    "Rectangle13_1": {},
    "Rectangle14": {},
    "Rectangle14_1": {},
    "Rectangle14_2": {},
    "Rectangle15": {},
    "Rectangle15_1": {},
    "Rectangle15_2": {},
    "Rectangle2_18": {},
    "Rectangle6": {},
    "Rectangle6_1": {},
    "Rectangle6_2": {},
    "Rectangle7_1": {},
    "ReqDescription_DataCard1": {},
    "ReqDescription_DataCard2": {},
    "ReqDescription_DataCard2_1": {},
    "ReqDescription_DataCard2_2": {},
    "ReqPermission_DataCard1": {},
    "ReqPermission_DataCard2": {},
    "ReqPermission_DataCard2_1": {},
    "ReqPermission_DataCard2_2": {},
    "ReqReason_DataCard1": {},
    "ReqReason_DataCard2": {},
    "ReqReason_DataCard2_1": {},
    "ReqReason_DataCard2_2": {},
    "ReqType_DataCard2": {},
    "ReqType_DataCard3": {},
    "ReqType_DataCard3_1": {},
    "ReqType_DataCard3_2": {},
    "Separator2": {},
    "StarVisible1": {},
    "StarVisible10": {},
    "StarVisible11": {},
    "StarVisible12": {},
    "StarVisible13": {},
    "StarVisible16": {},
    "StarVisible16_1": {},
    "StarVisible16_2": {},
    "StarVisible18": {},
    "StarVisible18_1": {},
    "StarVisible18_2": {},
    "StarVisible20": {},
    "StarVisible20_1": {},
    "StarVisible20_2": {},
    "StarVisible22": {},
    "StarVisible22_1": {},
    "StarVisible22_2": {},
    "StarVisible5": {},
    "StarVisible6": {},
    "StarVisible7": {},
    "StarVisible9": {},
    "Status_DataCard2": {},
    "Status_DataCard2_1": {},
    "Status_DataCard2_2": {},
    "Subtitle1": {},
    "Subtitle1_1": {},
    "Subtitle1_10": {},
    "Subtitle1_11": {},
    "Subtitle1_2": {},
    "Subtitle1_3": {},
    "Subtitle1_4": {},
    "Subtitle1_5": {},
    "Subtitle1_6": {},
    "Subtitle1_7": {},
    "Subtitle1_8": {},
    "Subtitle1_9": {},
    "TextBox2": {},
    "TextBox2_1": {},
    "TextBox2_10": {},
    "TextBox2_11": {},
    "TextBox2_2": {},
    "TextBox2_3": {},
    "TextBox2_4": {},
    "TextBox2_5": {},
    "TextBox2_6": {},
    "TextBox2_7": {},
    "TextBox2_8": {},
    "TextBox2_9": {},
    "TextBox3_2": {},
    "TextInput1": {},
    "TextInput1_1": {},
    "TextInput1_4": {},
    "TicketFilterPage": {},
    "TicketPage": {},
    "TicketsDetailPage_Approval": {},
    "TicketsDetailPage_HOD": {},
    "TicketsDetailPage_User": {},
    "TicketsGallery": {},
    "TicketsGallery_approval": {},
    "TicketsGallery_HOD": {},
    "Title_DataCard1": {},
    "Title_DataCard2": {},
    "Title_DataCard2_1": {},
    "Title_DataCard2_2": {},
    "Title2": {},
    "txtEmail": {}
  },
  "PCFDynamicSchemaForIRRetrievalEntry": {},
  "PCFTemplateEntry": {},
  "PublishOrderIndices": {
    "App": 0,
    "ApprovalPage": 3,
    "Attachments_DataCard1": 83,
    "Attachments_DataCard5": 158,
    "Attachments_DataCard6": 267,
    "Attachments_DataCard7": 211,
    "btn_approval": 33,
    "btn_approval_1": 273,
    "btn_approval_2": 217,
    "btn_HOD": 42,
    "btn_reject": 274,
    "btn_reject_1": 218,
    "btnLogin": 50,
    "Button_Cancel_10": 282,
    "Button_Cancel_11": 227,
    "Button_Cancel_14": 171,
    "Button_newticket": 89,
    "Button_OK_12": 170,
    "Button_OK_8": 281,
    "Button_OK_9": 226,
    "Container1": 0,
    "Container10": 117,
    "Container10_1": 172,
    "Container10_2": 228,
    "Container10_3": 276,
    "Container10_4": 220,
    "Container11": 88,
    "Container12": 283,
    "Container13": 177,
    "Container13_6": 164,
    "Container14": 288,
    "Container15": 233,
    "Container15_1": 280,
    "Container15_2": 225,
    "Container16": 309,
    "Container16_1": 277,
    "Container16_2": 221,
    "Container17": 310,
    "Container18": 313,
    "Container19": 324,
    "Container2": 1,
    "Container2_1": 52,
    "Container2_2": 91,
    "Container2_3": 118,
    "Container2_4": 95,
    "Container2_5": 284,
    "Container2_6": 301,
    "Container2_7": 173,
    "Container2_8": 325,
    "Container2_9": 229,
    "Container20": 272,
    "Container20_1": 216,
    "Container21": 314,
    "Container23": 315,
    "Container24": 318,
    "Container25": 333,
    "Container26": 334,
    "Container27": 337,
    "Container28": 338,
    "Container28_4": 169,
    "Container29": 339,
    "Container3": 5,
    "Container30": 342,
    "Container31": 102,
    "Container32": 103,
    "Container33": 106,
    "Container34": 107,
    "Container35": 108,
    "Container36": 111,
    "Container37": 124,
    "Container38": 56,
    "Container39": 8,
    "Container4": 6,
    "Container4_1": 47,
    "Container40": 12,
    "Container41": 16,
    "Container42": 166,
    "Container42_4": 165,
    "Container43": 21,
    "Container44": 25,
    "Container45": 29,
    "Container46": 291,
    "Container47": 292,
    "Container48": 294,
    "Container49": 295,
    "Container5": 19,
    "Container50": 222,
    "Container6": 35,
    "Container7": 51,
    "Container8": 44,
    "Container9": 90,
    "Container9_1": 300,
    "ContainerApproval": 32,
    "ContainerHOD": 41,
    "Created By_DataCard1": 153,
    "Created By_DataCard1_1": 206,
    "Created By_DataCard1_2": 262,
    "Created_DataCard1": 150,
    "Created_DataCard1_1": 203,
    "Created_DataCard1_2": 259,
    "DataCardKey1": 60,
    "DataCardKey10": 75,
    "DataCardKey11": 80,
    "DataCardKey12": 85,
    "DataCardKey13": 65,
    "DataCardKey14": 127,
    "DataCardKey14_1": 180,
    "DataCardKey14_2": 236,
    "DataCardKey17": 147,
    "DataCardKey17_1": 200,
    "DataCardKey17_2": 256,
    "DataCardKey20": 131,
    "DataCardKey20_1": 184,
    "DataCardKey20_2": 240,
    "DataCardKey22": 139,
    "DataCardKey22_1": 192,
    "DataCardKey22_2": 248,
    "DataCardKey23": 135,
    "DataCardKey23_1": 188,
    "DataCardKey23_2": 244,
    "DataCardKey24": 143,
    "DataCardKey24_1": 196,
    "DataCardKey24_2": 252,
    "DataCardKey26": 151,
    "DataCardKey26_1": 204,
    "DataCardKey26_2": 260,
    "DataCardKey27": 155,
    "DataCardKey27_1": 208,
    "DataCardKey27_2": 264,
    "DataCardKey5": 160,
    "DataCardKey6": 269,
    "DataCardKey7": 213,
    "DataCardKey9": 70,
    "DataCardValue1": 61,
    "DataCardValue10": 81,
    "DataCardValue11": 86,
    "DataCardValue12": 66,
    "DataCardValue13": 128,
    "DataCardValue13_1": 181,
    "DataCardValue13_2": 237,
    "DataCardValue16": 148,
    "DataCardValue16_1": 201,
    "DataCardValue16_2": 257,
    "DataCardValue19": 132,
    "DataCardValue19_1": 185,
    "DataCardValue19_2": 241,
    "DataCardValue21": 140,
    "DataCardValue21_1": 193,
    "DataCardValue21_2": 249,
    "DataCardValue22": 136,
    "DataCardValue22_1": 189,
    "DataCardValue22_2": 245,
    "DataCardValue23": 144,
    "DataCardValue23_1": 197,
    "DataCardValue23_2": 253,
    "DataCardValue25": 152,
    "DataCardValue25_1": 205,
    "DataCardValue25_2": 261,
    "DataCardValue26": 156,
    "DataCardValue26_1": 209,
    "DataCardValue26_2": 265,
    "DataCardValue5": 161,
    "DataCardValue6": 270,
    "DataCardValue7": 214,
    "DataCardValue8": 71,
    "DataCardValue9": 76,
    "Dialog_commentapproval": 219,
    "Dialog_commentHOD": 275,
    "Dialog_delete": 163,
    "ErrorMessage1": 62,
    "ErrorMessage10": 77,
    "ErrorMessage11": 82,
    "ErrorMessage12": 87,
    "ErrorMessage13": 67,
    "ErrorMessage16": 149,
    "ErrorMessage16_1": 202,
    "ErrorMessage16_2": 258,
    "ErrorMessage18": 133,
    "ErrorMessage18_1": 186,
    "ErrorMessage18_2": 242,
    "ErrorMessage20": 141,
    "ErrorMessage20_1": 194,
    "ErrorMessage20_2": 250,
    "ErrorMessage22": 157,
    "ErrorMessage22_1": 210,
    "ErrorMessage22_2": 266,
    "ErrorMessage5": 162,
    "ErrorMessage6": 271,
    "ErrorMessage7": 215,
    "ErrorMessage9": 72,
    "FilterByGallery": 289,
    "Form1": 57,
    "FormDetail_approval": 178,
    "FormDetail_user": 125,
    "FormDetail_user_2": 234,
    "Gallery1": 36,
    "galleryTemplate1": 37,
    "galleryTemplate1_2": 290,
    "galleryTemplate2": 99,
    "galleryTemplate2_1": 306,
    "galleryTemplate2_2": 330,
    "Group ,New Tickets": 11,
    "Group, All Ticket": 7,
    "Group, on hold": 20,
    "Group,Tickets Approval": 15,
    "Group21": 24,
    "Group6": 28,
    "Heading1": 104,
    "Heading1_1": 311,
    "Heading1_2": 105,
    "Heading1_3": 312,
    "Heading1_4": 336,
    "Heading1_5": 335,
    "HODPage": 28,
    "HomePage": 53,
    "Host": 0,
    "Icon1": 4,
    "Icon1_1": 53,
    "Icon1_10": 326,
    "Icon1_13": 230,
    "Icon1_2": 92,
    "Icon1_3": 119,
    "Icon1_4": 97,
    "Icon1_5": 121,
    "Icon1_6": 122,
    "Icon1_7": 285,
    "Icon1_8": 302,
    "Icon1_9": 174,
    "Icon2": 2,
    "icon3_2": 296,
    "icon8": 114,
    "icon8_1": 321,
    "icon8_2": 345,
    "Image1": 3,
    "Image1_1": 55,
    "Image1_2": 94,
    "Image1_3": 286,
    "Image1_4": 303,
    "Image1_5": 327,
    "Image1_6": 231,
    "Image1_7": 176,
    "Image1_8": 123,
    "Image2": 46,
    "Label1": 167,
    "Label1_1": 54,
    "Label1_2": 93,
    "Label1_3": 120,
    "Label1_4": 287,
    "Label1_5": 304,
    "Label1_6": 328,
    "Label1_7": 175,
    "Label1_8": 232,
    "Label1_9": 45,
    "Label2": 96,
    "Label2_1": 49,
    "Label3": 223,
    "Label4": 278,
    "LoginPage": 98,
    "NewTicketPage": 106,
    "NextArrow2": 40,
    "NextArrow2_2": 43,
    "NextArrow2_3": 34,
    "Rectangle1_12": 116,
    "Rectangle1_13": 323,
    "Rectangle1_14": 347,
    "Rectangle13_1": 293,
    "Rectangle14": 115,
    "Rectangle14_1": 322,
    "Rectangle14_2": 346,
    "Rectangle15": 101,
    "Rectangle15_1": 308,
    "Rectangle15_2": 332,
    "Rectangle2_18": 299,
    "Rectangle6": 100,
    "Rectangle6_1": 307,
    "Rectangle6_2": 331,
    "Rectangle7_1": 298,
    "ReqDescription_DataCard1": 78,
    "ReqDescription_DataCard2": 142,
    "ReqDescription_DataCard2_1": 195,
    "ReqDescription_DataCard2_2": 251,
    "ReqPermission_DataCard1": 68,
    "ReqPermission_DataCard2": 137,
    "ReqPermission_DataCard2_1": 190,
    "ReqPermission_DataCard2_2": 246,
    "ReqReason_DataCard1": 73,
    "ReqReason_DataCard2": 134,
    "ReqReason_DataCard2_1": 187,
    "ReqReason_DataCard2_2": 243,
    "ReqType_DataCard2": 63,
    "ReqType_DataCard3": 129,
    "ReqType_DataCard3_1": 182,
    "ReqType_DataCard3_2": 238,
    "Separator2": 38,
    "StarVisible1": 59,
    "StarVisible10": 74,
    "StarVisible11": 79,
    "StarVisible12": 84,
    "StarVisible13": 64,
    "StarVisible16": 146,
    "StarVisible16_1": 199,
    "StarVisible16_2": 255,
    "StarVisible18": 130,
    "StarVisible18_1": 183,
    "StarVisible18_2": 239,
    "StarVisible20": 138,
    "StarVisible20_1": 191,
    "StarVisible20_2": 247,
    "StarVisible22": 154,
    "StarVisible22_1": 207,
    "StarVisible22_2": 263,
    "StarVisible5": 159,
    "StarVisible6": 268,
    "StarVisible7": 212,
    "StarVisible9": 69,
    "Status_DataCard2": 145,
    "Status_DataCard2_1": 198,
    "Status_DataCard2_2": 254,
    "Subtitle1": 109,
    "Subtitle1_1": 113,
    "Subtitle1_10": 319,
    "Subtitle1_11": 343,
    "Subtitle1_2": 316,
    "Subtitle1_3": 320,
    "Subtitle1_4": 341,
    "Subtitle1_5": 344,
    "Subtitle1_6": 112,
    "Subtitle1_7": 110,
    "Subtitle1_8": 317,
    "Subtitle1_9": 340,
    "TextBox2": 10,
    "TextBox2_1": 14,
    "TextBox2_10": 17,
    "TextBox2_11": 18,
    "TextBox2_2": 27,
    "TextBox2_3": 31,
    "TextBox2_4": 23,
    "TextBox2_5": 9,
    "TextBox2_6": 13,
    "TextBox2_7": 26,
    "TextBox2_8": 30,
    "TextBox2_9": 22,
    "TextBox3_2": 297,
    "TextInput1": 279,
    "TextInput1_1": 224,
    "TextInput1_4": 168,
    "TicketFilterPage": 146,
    "TicketPage": 161,
    "TicketsDetailPage_Approval": 189,
    "TicketsDetailPage_HOD": 245,
    "TicketsDetailPage_User": 301,
    "TicketsGallery": 98,
    "TicketsGallery_approval": 305,
    "TicketsGallery_HOD": 329,
    "Title_DataCard1": 58,
    "Title_DataCard2": 126,
    "Title_DataCard2_1": 179,
    "Title_DataCard2_2": 235,
    "Title2": 39,
    "txtEmail": 48
  },
  "ResourcesJsonIndices": {
    "Image-Basel_Add": 0,
    "Image-Basel_Cancel": 1,
    "Image-Basel_Check": 2,
    "Image-Basel_ChevronLeft": 3,
    "Image-Basel_ChevronRight": 4,
    "Image-Basel_filter": 5,
    "Image-Basel_Search": 6,
    "Image-Logo - PizzaHut": 8,
    "Image-logocochu": 10,
    "Image-pizzahut1": 9,
    "Image-SampleImage": 7
  },
  "RuleScreenIdWithoutScreen": {},
  "TemplateVersions": {},
  "VolatileProperties": {
    "AnalysisLoadTime": 1.8362915,
    "ControlCount": {
      "attachments": 4,
      "button": 14,
      "combobox": 14,
      "form": 1,
      "formViewer": 3,
      "gallery": 5,
      "galleryTemplate": 5,
      "groupContainer": 83,
      "icon": 20,
      "image": 10,
      "label": 133,
      "rectangle": 16,
      "screen": 10,
      "text": 7,
      "typedDataCard": 33
    },
    "DeserializationLoadTime": 3.8232357
  },
  "WasLocalDatabaseReferencesEmpty": true
}